sylber/__init__.py
sylber/model/__init__.py
sylber/model/attend.py
sylber/model/ema_module.py
sylber/model/flowmatching.py
sylber/model/quantizer.py
sylber/model/segment_synthesis.py
sylber/model/sylber.py
sylber/model/sylber_trainer.py
sylber/utils/__init__.py
sylber/utils/lr_schedule.py
sylber/utils/misc.py
sylber/utils/noise_utils.py
sylber/utils/segment_utils.py
sylber-0.1.4.dist-info/LICENSE
sylber-0.1.4.dist-info/METADATA
sylber-0.1.4.dist-info/WHEEL
sylber-0.1.4.dist-info/top_level.txt
sylber-0.1.4.dist-info/RECORD
