Metadata-Version: 2.2
Name: sylber
Version: 0.1.4
Summary: Python code for "Sylber: Syllabic Embedding Representation of Speech from Raw Audio"
Home-page: https://github.com/Berkeley-Speech-Group/sylber
Author: Cheol Jun Cho, Nicholas Lee, Akshat Gupta, Dhruv Agarwal, Ethan Chen, Alan Black, Gopala Anumanchipalli
Author-email: cheoljun@berkeley.edu
License: Apache-2.0
Classifier: Programming Language :: Python :: 3
Classifier: License :: OSI Approved :: Apache Software License
Classifier: Operating System :: OS Independent
Requires-Python: >=3.8
License-File: LICENSE
Requires-Dist: numpy
Requires-Dist: soundfile
Requires-Dist: librosa
Requires-Dist: torch
Requires-Dist: torchaudio
Requires-Dist: transformers
Requires-Dist: huggingface-hub
Requires-Dist: tqdm
Requires-Dist: speech-articulatory-coding
Requires-Dist: torchode==1.0.0
Requires-Dist: torchdiffeq==0.2.4
Requires-Dist: beartype==0.19.0
Requires-Dist: gateloop-transformer==0.2.5
Requires-Dist: vector-quantize-pytorch==1.18.5
Requires-Dist: torchtyping==0.1.5
Dynamic: author
Dynamic: author-email
Dynamic: classifier
Dynamic: description
Dynamic: description-content-type
Dynamic: home-page
Dynamic: license
Dynamic: requires-dist
Dynamic: requires-python
Dynamic: summary
